pyby/__init__.py
pyby/enumerable.py
pyby/enumerable_dict.py
pyby/enumerable_list.py
pyby/enumerator.py
pyby/object.py
pyby-0.4.0.dist-info/LICENSE
pyby-0.4.0.dist-info/METADATA
pyby-0.4.0.dist-info/WHEEL
pyby-0.4.0.dist-info/top_level.txt
pyby-0.4.0.dist-info/RECORD
