Metadata-Version: 2.1
Name: pyby
Version: 0.4.0
Summary: A collection of Ruby behaviour ported to Python.
Home-page: https://devl.github.io/Pyby
Author: Lennart Fridén
Author-email: lennart@devl.se
License: MIT
Project-URL: Bug Reports, https://github.com/DevL/Pyby/issues
Project-URL: Source, https://github.com/DevL/Pyby
Keywords: Ruby Enumerable
Platform: UNKNOWN
Classifier: Development Status :: 2 - Pre-Alpha
Classifier: License :: OSI Approved :: MIT License
Classifier: Programming Language :: Python :: 3
Classifier: Programming Language :: Python :: 3.8
Classifier: Programming Language :: Python :: 3.9
Classifier: Programming Language :: Python :: 3.10
Classifier: Topic :: Software Development :: Libraries
Classifier: Topic :: Software Development :: Libraries :: Ruby Modules
Requires-Python: ~=3.8
